WACL/__init__.py
WACL/wacl.py
WACL/app/__init__.py
WACL/core/__init__.py
WACL/core/icacls.py
WACL/core/report.py
WACL/core/xlsx.py
WACL/sample/__init__.py
WACL/sample/test.py
WACL-0.0.1.dist-info/LICENSE
WACL-0.0.1.dist-info/METADATA
WACL-0.0.1.dist-info/WHEEL
WACL-0.0.1.dist-info/top_level.txt
WACL-0.0.1.dist-info/RECORD
