Metadata-Version: 2.1
Name: WACL
Version: 0.0.1
Summary: Windows ACL Get Package.
Author-email: yuhekun <3320382157@qq.com>
Project-URL: Homepage, https://github.com/yalisandsoso/WACL
Project-URL: Bug Tracker, https://github.com/yalisandsoso/WACL
Classifier: Programming Language :: Python :: 3
Classifier: License :: OSI Approved :: MIT License
Classifier: Operating System :: OS Independent
Requires-Python: >=3.6
License-File: LICENSE
Requires-Dist: openpyxl ==3.1.2
